pretty_genetic_algorithm/Creature.py
pretty_genetic_algorithm/PrettyGeneticAlgorithm.py
pretty_genetic_algorithm/__init__.py
pretty_genetic_algorithm/parameter/BaseParameter.py
pretty_genetic_algorithm/parameter/BoolParameter.py
pretty_genetic_algorithm/parameter/RangeParameter.py
pretty_genetic_algorithm/parameter/__init__.py
pretty_genetic_algorithm-0.0.4.2.dist-info/LICENSE
pretty_genetic_algorithm-0.0.4.2.dist-info/WHEEL
pretty_genetic_algorithm-0.0.4.2.dist-info/METADATA
pretty_genetic_algorithm-0.0.4.2.dist-info/RECORD
