Metadata-Version: 2.1
Name: pretty-genetic-algorithm
Version: 0.0.4.2
Summary: A genetic algorithm implementation with pretty progress updates
License: MIT
Author: eniallator
Requires-Python: >=3.8,<4.0
Classifier: License :: OSI Approved :: MIT License
Classifier: Programming Language :: Python :: 3
Classifier: Programming Language :: Python :: 3.8
Classifier: Programming Language :: Python :: 3.9
Classifier: Programming Language :: Python :: 3.10
Requires-Dist: ipywidgets (>=7.7.0,<8.0.0)
Requires-Dist: jupyter (>=1.0.0,<2.0.0)
Requires-Dist: packaging (>=21.3,<22.0)
Requires-Dist: tqdm (>=4.63.0,<5.0.0)
